gisus/__init__.py
gisus/common.py
gisus/gisus.py
gisus-0.0.2.dist-info/LICENSE
gisus-0.0.2.dist-info/METADATA
gisus-0.0.2.dist-info/WHEEL
gisus-0.0.2.dist-info/entry_points.txt
gisus-0.0.2.dist-info/top_level.txt
gisus-0.0.2.dist-info/RECORD
